pytc111/__init__.py
pytc111/tc111.py
pytc111-3.1.0.dist-info/METADATA
pytc111-3.1.0.dist-info/WHEEL
pytc111-3.1.0.dist-info/top_level.txt
pytc111-3.1.0.dist-info/RECORD
