Metadata-Version: 2.1
Name: pytc111
Version: 3.1.0
Summary: tc local package
Home-page: https://github.com/tiacui/testrepo111
Author: someone111
Author-email: tc@tc111xyz.com
License: UNKNOWN
Platform: UNKNOWN
Classifier: Programming Language :: Python :: 3
Classifier: License :: OSI Approved :: MIT License
Classifier: Operating System :: OS Independent
Requires-Python: >=3.6
